odoo/addons/delivery_send_to_shipper_at_operation/README.rst
odoo/addons/delivery_send_to_shipper_at_operation/__init__.py
odoo/addons/delivery_send_to_shipper_at_operation/__manifest__.py
odoo/addons/delivery_send_to_shipper_at_operation/i18n/delivery_send_to_shipper_at_operation.pot
odoo/addons/delivery_send_to_shipper_at_operation/models/__init__.py
odoo/addons/delivery_send_to_shipper_at_operation/models/delivery_carrier.py
odoo/addons/delivery_send_to_shipper_at_operation/models/stock_picking.py
odoo/addons/delivery_send_to_shipper_at_operation/readme/CONTRIBUTORS.rst
odoo/addons/delivery_send_to_shipper_at_operation/readme/DESCRIPTION.rst
odoo/addons/delivery_send_to_shipper_at_operation/readme/ROADMAP.rst
odoo/addons/delivery_send_to_shipper_at_operation/readme/USAGE.rst
odoo/addons/delivery_send_to_shipper_at_operation/static/description/delivery_carrier1.png
odoo/addons/delivery_send_to_shipper_at_operation/static/description/delivery_carrier2.png
odoo/addons/delivery_send_to_shipper_at_operation/static/description/icon.png
odoo/addons/delivery_send_to_shipper_at_operation/static/description/index.html
odoo/addons/delivery_send_to_shipper_at_operation/tests/__init__.py
odoo/addons/delivery_send_to_shipper_at_operation/tests/test_send_to_shipper.py
odoo/addons/delivery_send_to_shipper_at_operation/views/delivery_carrier.xml
odoo/addons/delivery_send_to_shipper_at_operation/views/stock_picking.xml
odoo13_addon_delivery_send_to_shipper_at_operation-13.0.1.0.1.dev5.dist-info/METADATA
odoo13_addon_delivery_send_to_shipper_at_operation-13.0.1.0.1.dev5.dist-info/WHEEL
odoo13_addon_delivery_send_to_shipper_at_operation-13.0.1.0.1.dev5.dist-info/top_level.txt
odoo13_addon_delivery_send_to_shipper_at_operation-13.0.1.0.1.dev5.dist-info/RECORD
