Metadata-Version: 2.1
Name: odoo13-addon-delivery-send-to-shipper-at-operation
Version: 13.0.1.0.1.dev5
Summary: Send delivery notice to the shipper from any operation.
Home-page: https://github.com/OCA/delivery-carrier
Author: Camptocamp, Odoo Community Association (OCA)
Author-email: support@odoo-community.org
License: AGPL-3
Platform: UNKNOWN
Classifier: Programming Language :: Python
Classifier: Framework :: Odoo
Classifier: Framework :: Odoo :: 13.0
Classifier: License :: OSI Approved :: GNU Affero General Public License v3
Classifier: Development Status :: 4 - Beta
Requires-Python: >=3.5
Requires-Dist: odoo13-addon-stock-picking-delivery-link
Requires-Dist: odoo <13.1dev,>=13.0a
